loadcalculation/ChineseStandardDeck.pyd
loadcalculation/SingSunCPPCodeGenerate.pyd
loadcalculation/SingSunCPPDeck.pyd
loadcalculation/SingSunSTDUDeck.pyd
loadcalculation/__init__.py
loadcalculation-0.1.dist-info/METADATA
loadcalculation-0.1.dist-info/WHEEL
loadcalculation-0.1.dist-info/top_level.txt
loadcalculation-0.1.dist-info/RECORD
